{"cameraMode":{"drawMode":0,"name":"Shaded","section":"Shading Mode"},"sceneLighting":true,"audioPlay":false,"sceneViewState":{"m_AlwaysRefresh":false,"showFog":true,"showSkybox":true,"showFlares":true,"showImageEffects":true,"showParticleSystems":true,"showVisualEffectGraphs":true,"m_FxEnabled":true},"in2DMode":false,"pivot":{"x":3.9127721786499025,"y":0.7739677429199219,"z":2.7073097229003908},"rotation":{"x":0.34088441729545596,"y":0.18936818838119508,"z":-0.07030919194221497,"w":0.9181501865386963},"size":14.133451461791993,"orthographic":false}